CompArch/Lab_exc/Solns/lab1q1.v
module bcd2gray_gate (g,b);
input [3:0]b;
output [3:0]g;
xor(g[3],b[3],0);
xor(g[2],b[3],b[2]);
xor(g[1],b[2],b[1]);
xor(g[0],b[1],b[0]);
endmodule

module testbench;
reg [3:0]b;
wire [3:0]g;
bcd2gray_gate bgate(g,b);
initial
begin
$dumpfile("firstgtk.vcd");
$dumpvars;
$monitor($time," Input : b=%4b   Output : g = %4b",b,g);
#0 b=4'b0000;
#2 b=4'b0001;
#2 b=4'b0010;
#2 b=4'b0011;
#2 b=4'b0100;
#2 b=4'b0110;
#2 b=4'b0111;
#2 b=4'b1000;
#2 b=4'b1001;
#2 b=4'b0101;
#2 $finish;
end
endmodule

CompArch/Lab_exc/Solns/firstgtk.vcd
$date
	Thu Nov 05 22:50:09 2020
$end
$version
	Icarus Verilog
$end
$timescale
	1s
$end
$scope module testbench $end
$var wire 4 ! g [3:0] $end
$var reg 4 " b [3:0] $end
$scope module bgate $end
$var wire 4 # b [3:0] $end
$var wire 4 $ g [3:0] $end
$upscope $end
$upscope $end
$enddefinitions $end
#0
$dumpvars
b0 $
b0 #
b0 "
b0 !
$end
#2
b1 !
b1 $
b1 "
b1 #
#4
b11 !
b11 $
b10 "
b10 #
#6
b10 !
b10 $
b11 "
b11 #
#8
b110 !
b110 $
b100 "
b100 #
#10
b101 !
b101 $
b110 "
b110 #
#12
b100 !
b100 $
b111 "
b111 #
#14
b1100 !
b1100 $
b1000 "
b1000 #
#16
b1101 !
b1101 $
b1001 "
b1001 #
#18
b111 !
b111 $
b101 "
b101 #
